__init__.py
query_doc.py
query_doc-1.0.4.dist-info/LICENSE
query_doc-1.0.4.dist-info/METADATA
query_doc-1.0.4.dist-info/WHEEL
query_doc-1.0.4.dist-info/top_level.txt
query_doc-1.0.4.dist-info/RECORD
