Metadata-Version: 2.1
Name: query_doc
Version: 1.0.4
Summary: A small package that allows you to break your query in manageable chunks (normally fields), allowing you to focus on building each variable / field independently, with notes / documentation and at the end cam be compiled to a single gigantic query string that otherwise would be impossible to manage or maintain
Author-email: Real Data-Driven <real.datadriven@gmail.com>
Project-URL: Homepage, https://github.com/realdatadriven/query_doc
Project-URL: Bug Tracker, https://github.com/realdatadriven/query_doc/issues
Classifier: Programming Language :: Python :: 3
Classifier: License :: OSI Approved :: MIT License
Classifier: Operating System :: OS Independent
Requires-Python: >=3.7
License-File: LICENSE
